msbase/__init__.py
msbase/argparse_.py
msbase/assert_.py
msbase/lab.py
msbase/logging.py
msbase/mysql.py
msbase/subprocess_.py
msbase/utils.py
msbase-0.3.4.data/scripts/ck
msbase-0.3.4.data/scripts/j2y
msbase-0.3.4.data/scripts/y2j
msbase-0.3.4.data/scripts/yl
msbase-0.3.4.dist-info/LICENSE
msbase-0.3.4.dist-info/METADATA
msbase-0.3.4.dist-info/WHEEL
msbase-0.3.4.dist-info/top_level.txt
msbase-0.3.4.dist-info/RECORD
