Metadata-Version: 2.1
Name: msbase
Version: 0.3.4
Summary: Base Library for Python for MySelf
Home-page: https://github.com/izgzhen/msbase.py
Author: Zhen Zhang
Author-email: pip@zhen-zhang.com
License: UNKNOWN
Platform: UNKNOWN
Classifier: Programming Language :: Python :: 3
Classifier: License :: OSI Approved :: MIT License
Classifier: Operating System :: OS Independent
Requires-Dist: termcolor (==1.1.0)
Requires-Dist: jsonlines (==1.2.0)
Requires-Dist: tabulate
Requires-Dist: PyYAML (==5.3.1)
